carthageai.py
carthageai-0.1.0.dist-info/licenses/LICENSE
carthageai-0.1.0.dist-info/METADATA
carthageai-0.1.0.dist-info/WHEEL
carthageai-0.1.0.dist-info/entry_points.txt
carthageai-0.1.0.dist-info/top_level.txt
carthageai-0.1.0.dist-info/RECORD
