Metadata-Version: 2.4
Name: carthageai
Version: 0.1.0
Summary: AI Terminal Assistant with multi-provider support
Author-email: alaadotcom <ala.dotcom@hotmail.com>
License: MIT
Classifier: Development Status :: 3 - Alpha
Classifier: Intended Audience :: Developers
Classifier: Intended Audience :: System Administrators
Classifier: License :: OSI Approved :: MIT License
Classifier: Programming Language :: Python :: 3
Requires-Python: >=3.8
License-File: LICENSE
Dynamic: license-file
